ghstreak/__init__.py
ghstreak/streak.py
github_streak-0.1.0.dist-info/METADATA
github_streak-0.1.0.dist-info/WHEEL
github_streak-0.1.0.dist-info/entry_points.txt
github_streak-0.1.0.dist-info/top_level.txt
github_streak-0.1.0.dist-info/RECORD
