Metadata-Version: 2.4
Name: github-streak
Version: 0.1.0
Summary: CLI tool to track your GitHub contribution streaks
Author: Deven Mistry
Project-URL: Homepage, https://github.com/deven367/github-streak
Project-URL: Repository, https://github.com/deven367/github-streak
Classifier: Programming Language :: Python :: 3
Classifier: Programming Language :: Python :: 3.7
Classifier: Programming Language :: Python :: 3.8
Classifier: Programming Language :: Python :: 3.9
Classifier: Programming Language :: Python :: 3.10
Classifier: Programming Language :: Python :: 3.11
Classifier: Operating System :: OS Independent
Classifier: License :: OSI Approved :: MIT License
Requires-Python: >=3.7
Requires-Dist: requests>=2.25.0
Requires-Dist: python-dotenv>=0.19.0
